AUTHORS
LICENSE
MANIFEST.in
requirements.txt
setup.py
blogger/__init__.py
blogger/admin.py
blogger/context_processors.py
blogger/feeds.py
blogger/managers.py
blogger/models.py
blogger/permissions.py
blogger/serializers.py
blogger/urls.py
blogger/views.py
blogger/tests/__init__.py
blogger/tests/admin.py
blogger/tests/context_processors.py
blogger/tests/feeds.py
blogger/tests/managers.py
blogger/tests/models.py
blogger/tests/views.py
blogger/themes/__init__.py
blogger/themes/3col/__init__.py
blogger/themes/3col/static/3col/jquery-1.8.3.min.js
blogger/themes/3col/static/3col/bootstrap/css/bootstrap.min.css
blogger/themes/3col/static/3col/bootstrap/js/bootstrap.min.js
blogger/themes/3col/templates/base.html
blogger/themes/3col/templates/list.html
blogger/themes/3col/templates/view_post.html
blogger/themes/default/__init__.py
blogger/themes/default/static/jquery-1.8.3.min.js
blogger/themes/default/static/bootstrap/css/bootstrap.min.css
blogger/themes/default/static/bootstrap/js/bootstrap.min.js
blogger/themes/default/templates/base.html
blogger/themes/default/templates/list.html
blogger/themes/default/templates/view_post.html
django_blogger.egg-info/PKG-INFO
django_blogger.egg-info/SOURCES.txt
django_blogger.egg-info/dependency_links.txt
django_blogger.egg-info/requires.txt
django_blogger.egg-info/top_level.txt