Metadata-Version: 1.0
Name: django-blogger
Version: 1.0.0.6
Summary: A package to administer a simple blog via Django.
Home-page: https://github.com/jhgaylor/django-blogger/
Author: Jake Gaylor
Author-email: jake@codegur.us
License: UNKNOWN
Platform: UNKNOWN
